{"Mass/kg": 39193.272120000001, "Size_x/m": 10.0, "Height_of_vault/m": 1.299269, "Thickness/m": 0.095000000000000001, "Height_of_each_node/m": {"0": {"coordinates": "{0, 0, 0}", "height": "0"}, "1": {"coordinates": "{1, 0, 0}", "height": "0"}, "2": {"coordinates": "{2, 0, 0}", "height": "0"}, "3": {"coordinates": "{3, 0, 0}", "height": "0"}, "4": {"coordinates": "{4, 0, 0}", "height": "0"}, "5": {"coordinates": "{5, 0, 0}", "height": "0"}, "6": {"coordinates": "{6, 0, 0}", "height": "0"}, "7": {"coordinates": "{7, 0, 0}", "height": "0"}, "8": {"coordinates": "{8, 0, 0}", "height": "0"}, "9": {"coordinates": "{9, 0, 0}", "height": "0"}, "10": {"coordinates": "{10, 0, 0}", "height": "0"}, "11": {"coordinates": "{11, 0, 0}", "height": "0"}, "12": {"coordinates": "{12, 0, 0}", "height": "0"}, "13": {"coordinates": "{13, 0, 0}", "height": "0"}, "14": {"coordinates": "{14, 0, 0}", "height": "0"}, "15": {"coordinates": "{15, 0, 0}", "height": "0"}, "16": {"coordinates": "{0, 1, 0}", "height": "0"}, "17": {"coordinates": "{15, 1, 0}", "height": "0"}, "18": {"coordinates": "{0, 2, 0}", "height": "0"}, "19": {"coordinates": "{15, 2, 0}", "height": "0"}, "20": {"coordinates": "{0, 3, 0}", "height": "0"}, "21": {"coordinates": "{15, 3, 0}", "height": "0"}, "22": {"coordinates": "{0, 4, 0}", "height": "0"}, "23": {"coordinates": "{15, 4, 0}", "height": "0"}, "24": {"coordinates": "{0, 5, 0}", "height": "0"}, "25": {"coordinates": "{15, 5, 0}", "height": "0"}, "26": {"coordinates": "{0, 6, 0}", "height": "0"}, "27": {"coordinates": "{15, 6, 0}", "height": "0"}, "28": {"coordinates": "{0, 7, 0}", "height": "0"}, "29": {"coordinates": "{15, 7, 0}", "height": "0"}, "30": {"coordinates": "{0, 8, 0}", "height": "0"}, "31": {"coordinates": "{15, 8, 0}", "height": "0"}, "32": {"coordinates": "{0, 9, 0}", "height": "0"}, "33": {"coordinates": "{15, 9, 0}", "height": "0"}, "34": {"coordinates": "{0, 10, 0}", "height": "0"}, "35": {"coordinates": "{1, 10, 0}", "height": "0"}, "36": {"coordinates": "{2, 10, 0}", "height": "0"}, "37": {"coordinates": "{3, 10, 0}", "height": "0"}, "38": {"coordinates": "{4, 10, 0}", "height": "0"}, "39": {"coordinates": "{5, 10, 0}", "height": "0"}, "40": {"coordinates": "{6, 10, 0}", "height": "0"}, "41": {"coordinates": "{7, 10, 0}", "height": "0"}, "42": {"coordinates": "{8, 10, 0}", "height": "0"}, "43": {"coordinates": "{9, 10, 0}", "height": "0"}, "44": {"coordinates": "{10, 10, 0}", "height": "0"}, "45": {"coordinates": "{11, 10, 0}", "height": "0"}, "46": {"coordinates": "{12, 10, 0}", "height": "0"}, "47": {"coordinates": "{13, 10, 0}", "height": "0"}, "48": {"coordinates": "{14, 10, 0}", "height": "0"}, "49": {"coordinates": "{15, 10, 0}", "height": "0"}, "50": {"coordinates": "{1, 1, 0}", "height": "0.212343"}, "51": {"coordinates": "{2, 1, 0}", "height": "0.272461"}, "52": {"coordinates": "{3, 1, 0}", "height": "0.350573"}, "53": {"coordinates": "{4, 1, 0}", "height": "0.302929"}, "54": {"coordinates": "{5, 1, 0}", "height": "0.40779"}, "55": {"coordinates": "{6, 1, 0}", "height": "0.607376"}, "56": {"coordinates": "{7, 1, 0}", "height": "0.689505"}, "57": {"coordinates": "{8, 1, 0}", "height": "0.651635"}, "58": {"coordinates": "{9, 1, 0}", "height": "0.536454"}, "59": {"coordinates": "{10, 1, 0}", "height": "0.489314"}, "60": {"coordinates": "{11, 1, 0}", "height": "0.553084"}, "61": {"coordinates": "{12, 1, 0}", "height": "0.214781"}, "62": {"coordinates": "{13, 1, 0}", "height": "0.211351"}, "63": {"coordinates": "{14, 1, 0}", "height": "0.232927"}, "64": {"coordinates": "{1, 2, 0}", "height": "0.218908"}, "65": {"coordinates": "{2, 2, 0}", "height": "0.373756"}, "66": {"coordinates": "{3, 2, 0}", "height": "0.48478"}, "67": {"coordinates": "{4, 2, 0}", "height": "0.544035"}, "68": {"coordinates": "{5, 2, 0}", "height": "0.663302"}, "69": {"coordinates": "{6, 2, 0}", "height": "0.775386"}, "70": {"coordinates": "{7, 2, 0}", "height": "0.832342"}, "71": {"coordinates": "{8, 2, 0}", "height": "0.831785"}, "72": {"coordinates": "{9, 2, 0}", "height": "0.779024"}, "73": {"coordinates": "{10, 2, 0}", "height": "0.695873"}, "74": {"coordinates": "{11, 2, 0}", "height": "0.576978"}, "75": {"coordinates": "{12, 2, 0}", "height": "0.392809"}, "76": {"coordinates": "{13, 2, 0}", "height": "0.312033"}, "77": {"coordinates": "{14, 2, 0}", "height": "0.19108"}, "78": {"coordinates": "{1, 3, 0}", "height": "0.234267"}, "79": {"coordinates": "{2, 3, 0}", "height": "0.426161"}, "80": {"coordinates": "{3, 3, 0}", "height": "0.574932"}, "81": {"coordinates": "{4, 3, 0}", "height": "0.686136"}, "82": {"coordinates": "{5, 3, 0}", "height": "0.800922"}, "83": {"coordinates": "{6, 3, 0}", "height": "0.884165"}, "84": {"coordinates": "{7, 3, 0}", "height": "0.926776"}, "85": {"coordinates": "{8, 3, 0}", "height": "0.927551"}, "86": {"coordinates": "{9, 3, 0}", "height": "0.885611"}, "87": {"coordinates": "{10, 3, 0}", "height": "0.799729"}, "88": {"coordinates": "{11, 3, 0}", "height": "0.67093"}, "89": {"coordinates": "{12, 3, 0}", "height": "0.505584"}, "90": {"coordinates": "{13, 3, 0}", "height": "0.375155"}, "91": {"coordinates": "{14.0, 3, 0}", "height": "0.207357"}, "92": {"coordinates": "{1, 4, 0}", "height": "0.309221"}, "93": {"coordinates": "{2, 4, 0}", "height": "0.519433"}, "94": {"coordinates": "{3, 4, 0}", "height": "0.687685"}, "95": {"coordinates": "{4, 4, 0}", "height": "0.772718"}, "96": {"coordinates": "{5, 4, 0}", "height": "0.926649"}, "97": {"coordinates": "{6, 4, 0}", "height": "1.085355"}, "98": {"coordinates": "{7, 4, 0}", "height": "1.159877"}, "99": {"coordinates": "{8, 4, 0}", "height": "1.147804"}, "100": {"coordinates": "{9, 4, 0}", "height": "1.063878"}, "101": {"coordinates": "{10, 4, 0}", "height": "0.961592"}, "102": {"coordinates": "{11, 4, 0}", "height": "0.838551"}, "103": {"coordinates": "{12, 4, 0}", "height": "0.569228"}, "104": {"coordinates": "{13, 4, 0}", "height": "0.446711"}, "105": {"coordinates": "{14, 4.0, 0}", "height": "0.286851"}, "106": {"coordinates": "{1, 5, 0}", "height": "0.266024"}, "107": {"coordinates": "{2, 5.0, 0}", "height": "0.485375"}, "108": {"coordinates": "{3, 5, 0}", "height": "0.658599"}, "109": {"coordinates": "{4, 5, 0}", "height": "0.789487"}, "110": {"coordinates": "{5, 5, 0}", "height": "0.915462"}, "111": {"coordinates": "{6, 5, 0}", "height": "1.005758"}, "112": {"coordinates": "{7, 5, 0}", "height": "1.051047"}, "113": {"coordinates": "{8, 5.0, 0}", "height": "1.050281"}, "114": {"coordinates": "{9, 5.0, 0}", "height": "1.003018"}, "115": {"coordinates": "{10, 5, 0}", "height": "0.909331"}, "116": {"coordinates": "{11, 5, 0}", "height": "0.769957"}, "117": {"coordinates": "{12, 5, 0}", "height": "0.588204"}, "118": {"coordinates": "{13, 5.0, 0}", "height": "0.434006"}, "119": {"coordinates": "{14, 5.0, 0}", "height": "0.239375"}, "120": {"coordinates": "{1, 6.0, 0}", "height": "0.259533"}, "121": {"coordinates": "{2.0, 6, 0}", "height": "0.472044"}, "122": {"coordinates": "{3.0, 6.0, 0}", "height": "0.638024"}, "123": {"coordinates": "{4.0, 6.0, 0}", "height": "0.761968"}, "124": {"coordinates": "{5.0, 6.0, 0}", "height": "0.886898"}, "125": {"coordinates": "{6.0, 6.0, 0}", "height": "0.977906"}, "126": {"coordinates": "{7.0, 6.0, 0}", "height": "1.023965"}, "127": {"coordinates": "{8.0, 6.0, 0}", "height": "1.023878"}, "128": {"coordinates": "{9.0, 6.0, 0}", "height": "0.977251"}, "129": {"coordinates": "{10.0, 6, 0}", "height": "0.884613"}, "130": {"coordinates": "{11, 6, 0}", "height": "0.745319"}, "131": {"coordinates": "{12, 6, 0}", "height": "0.566285"}, "132": {"coordinates": "{13, 6, 0}", "height": "0.419758"}, "133": {"coordinates": "{14, 6, 0}", "height": "0.232189"}, "134": {"coordinates": "{1, 7, 0}", "height": "0.381361"}, "135": {"coordinates": "{2, 7, 0}", "height": "0.536338"}, "136": {"coordinates": "{3, 7, 0}", "height": "0.703879"}, "137": {"coordinates": "{4.0, 7.0, 0}", "height": "0.682569"}, "138": {"coordinates": "{5.0, 7.0, 0}", "height": "0.867478"}, "139": {"coordinates": "{6.0, 7.0, 0}", "height": "1.171873"}, "140": {"coordinates": "{7.0, 7.0, 0}", "height": "1.299269"}, "141": {"coordinates": "{8.0, 7.0, 0}", "height": "1.246015"}, "142": {"coordinates": "{9.0, 7.0, 0}", "height": "1.071311"}, "143": {"coordinates": "{10.0, 7.0, 0}", "height": "0.973752"}, "144": {"coordinates": "{11.0, 7, 0}", "height": "1.056411"}, "145": {"coordinates": "{12, 7, 0}", "height": "0.494849"}, "146": {"coordinates": "{13, 7, 0}", "height": "0.436745"}, "147": {"coordinates": "{14.0, 7, 0}", "height": "0.405234"}, "148": {"coordinates": "{1, 8, 0}", "height": "0.2818"}, "149": {"coordinates": "{2, 8, 0}", "height": "0.432394"}, "150": {"coordinates": "{3, 8.0, 0}", "height": "0.540839"}, "151": {"coordinates": "{4.0, 8.0, 0}", "height": "0.545075"}, "152": {"coordinates": "{5.0, 8.0, 0}", "height": "0.702775"}, "153": {"coordinates": "{6.0, 8.0, 0}", "height": "0.903306"}, "154": {"coordinates": "{7.0, 8.0, 0}", "height": "0.99823"}, "155": {"coordinates": "{8.0, 8.0, 0}", "height": "0.9834"}, "156": {"coordinates": "{9.0, 8.0, 0}", "height": "0.883275"}, "157": {"coordinates": "{10.0, 8.0, 0}", "height": "0.7877"}, "158": {"coordinates": "{11, 8.0, 0}", "height": "0.67839"}, "159": {"coordinates": "{12, 8, 0}", "height": "0.389711"}, "160": {"coordinates": "{13, 8, 0}", "height": "0.344939"}, "161": {"coordinates": "{14.0, 8, 0}", "height": "0.258408"}, "162": {"coordinates": "{1.0, 9.0, 0}", "height": "0.112379"}, "163": {"coordinates": "{2.0, 9.0, 0}", "height": "0.2013"}, "164": {"coordinates": "{3.0, 9.0, 0}", "height": "0.267444"}, "165": {"coordinates": "{4.0, 9.0, 0}", "height": "0.313832"}, "166": {"coordinates": "{5.0, 9.0, 0}", "height": "0.372616"}, "167": {"coordinates": "{6.0, 9.0, 0}", "height": "0.41823"}, "168": {"coordinates": "{7.0, 9.0, 0}", "height": "0.442098"}, "169": {"coordinates": "{8.0, 9.0, 0}", "height": "0.443337"}, "170": {"coordinates": "{9.0, 9.0, 0}", "height": "0.421748"}, "171": {"coordinates": "{10.0, 9.0, 0}", "height": "0.377953"}, "172": {"coordinates": "{11, 9, 0}", "height": "0.3123"}, "173": {"coordinates": "{12, 9, 0}", "height": "0.226543"}, "174": {"coordinates": "{13, 9, 0}", "height": "0.17152"}, "175": {"coordinates": "{14, 9, 0}", "height": "0.096829"}}, "Size_y/m": 15.0}