{"Mass/kg": 28267.729080000001, "Size_x/m": 10.0, "Height_of_vault/m": 1.5473570000000001, "Thickness/m": 0.035000000000000003, "Height_of_each_node/m": {"0": {"coordinates": "{0, 0, 0}", "height": "0"}, "1": {"coordinates": "{1, 0, 0}", "height": "0"}, "2": {"coordinates": "{2, 0, 0}", "height": "0"}, "3": {"coordinates": "{3, 0, 0}", "height": "0"}, "4": {"coordinates": "{4, 0, 0}", "height": "0"}, "5": {"coordinates": "{5, 0, 0}", "height": "0"}, "6": {"coordinates": "{6, 0, 0}", "height": "0"}, "7": {"coordinates": "{7, 0, 0}", "height": "0"}, "8": {"coordinates": "{8, 0, 0}", "height": "0"}, "9": {"coordinates": "{9, 0, 0}", "height": "0"}, "10": {"coordinates": "{10, 0, 0}", "height": "0"}, "11": {"coordinates": "{11, 0, 0}", "height": "0"}, "12": {"coordinates": "{12, 0, 0}", "height": "0"}, "13": {"coordinates": "{13, 0, 0}", "height": "0"}, "14": {"coordinates": "{14, 0, 0}", "height": "0"}, "15": {"coordinates": "{15, 0, 0}", "height": "0"}, "16": {"coordinates": "{0, 1, 0}", "height": "0"}, "17": {"coordinates": "{15, 1, 0}", "height": "0"}, "18": {"coordinates": "{0, 2, 0}", "height": "0"}, "19": {"coordinates": "{15, 2, 0}", "height": "0"}, "20": {"coordinates": "{0, 3, 0}", "height": "0"}, "21": {"coordinates": "{15, 3, 0}", "height": "0"}, "22": {"coordinates": "{0, 4, 0}", "height": "0"}, "23": {"coordinates": "{15, 4, 0}", "height": "0"}, "24": {"coordinates": "{0, 5, 0}", "height": "0"}, "25": {"coordinates": "{15, 5, 0}", "height": "0"}, "26": {"coordinates": "{0, 6, 0}", "height": "0"}, "27": {"coordinates": "{15, 6, 0}", "height": "0"}, "28": {"coordinates": "{0, 7, 0}", "height": "0"}, "29": {"coordinates": "{15, 7, 0}", "height": "0"}, "30": {"coordinates": "{0, 8, 0}", "height": "0"}, "31": {"coordinates": "{15, 8, 0}", "height": "0"}, "32": {"coordinates": "{0, 9, 0}", "height": "0"}, "33": {"coordinates": "{15, 9, 0}", "height": "0"}, "34": {"coordinates": "{0, 10, 0}", "height": "0"}, "35": {"coordinates": "{1, 10, 0}", "height": "0"}, "36": {"coordinates": "{2, 10, 0}", "height": "0"}, "37": {"coordinates": "{3, 10, 0}", "height": "0"}, "38": {"coordinates": "{4, 10, 0}", "height": "0"}, "39": {"coordinates": "{5, 10, 0}", "height": "0"}, "40": {"coordinates": "{6, 10, 0}", "height": "0"}, "41": {"coordinates": "{7, 10, 0}", "height": "0"}, "42": {"coordinates": "{8, 10, 0}", "height": "0"}, "43": {"coordinates": "{9, 10, 0}", "height": "0"}, "44": {"coordinates": "{10, 10, 0}", "height": "0"}, "45": {"coordinates": "{11, 10, 0}", "height": "0"}, "46": {"coordinates": "{12, 10, 0}", "height": "0"}, "47": {"coordinates": "{13, 10, 0}", "height": "0"}, "48": {"coordinates": "{14, 10, 0}", "height": "0"}, "49": {"coordinates": "{15, 10, 0}", "height": "0"}, "50": {"coordinates": "{1.0, 1.0, 0}", "height": "0.16008"}, "51": {"coordinates": "{2.0, 1.0, 0}", "height": "0.433825"}, "52": {"coordinates": "{3.0, 1.0, 0}", "height": "0.480663"}, "53": {"coordinates": "{4.0, 1.0, 0}", "height": "0.456938"}, "54": {"coordinates": "{5.0, 1.0, 0}", "height": "0.614146"}, "55": {"coordinates": "{6.0, 1.0, 0}", "height": "0.794461"}, "56": {"coordinates": "{7.0, 1.0, 0}", "height": "0.971006"}, "57": {"coordinates": "{8.0, 1.0, 0}", "height": "0.913152"}, "58": {"coordinates": "{9.0, 1.0, 0}", "height": "0.126624"}, "59": {"coordinates": "{10.0, 1.0, 0}", "height": "0.212257"}, "60": {"coordinates": "{11.0, 1.0, 0}", "height": "0.367527"}, "61": {"coordinates": "{12.0, 1.0, 0}", "height": "0.324607"}, "62": {"coordinates": "{13.0, 1, 0}", "height": "0.541208"}, "63": {"coordinates": "{14, 1, 0}", "height": "0.347602"}, "64": {"coordinates": "{1.0, 2.0, 0}", "height": "0.274224"}, "65": {"coordinates": "{2.0, 2.0, 0}", "height": "0.551529"}, "66": {"coordinates": "{3.0, 2.0, 0}", "height": "0.708771"}, "67": {"coordinates": "{4.0, 2.0, 0}", "height": "0.782202"}, "68": {"coordinates": "{5.0, 2.0, 0}", "height": "0.889182"}, "69": {"coordinates": "{6.0, 2.0, 0}", "height": "0.924141"}, "70": {"coordinates": "{7.0, 2.0, 0}", "height": "0.843077"}, "71": {"coordinates": "{8.0, 2.0, 0}", "height": "0.616988"}, "72": {"coordinates": "{9.0, 2.0, 0}", "height": "0.242819"}, "73": {"coordinates": "{10.0, 2.0, 0}", "height": "0.364813"}, "74": {"coordinates": "{11.0, 2.0, 0}", "height": "0.482801"}, "75": {"coordinates": "{12.0, 2.0, 0}", "height": "0.48993"}, "76": {"coordinates": "{13.0, 2, 0}", "height": "0.466997"}, "77": {"coordinates": "{14.0, 2, 0}", "height": "0.302092"}, "78": {"coordinates": "{1.0, 3.0, 0}", "height": "0.345061"}, "79": {"coordinates": "{2.0, 3.0, 0}", "height": "0.631316"}, "80": {"coordinates": "{3.0, 3.0, 0}", "height": "0.837834"}, "81": {"coordinates": "{4.0, 3.0, 0}", "height": "0.962349"}, "82": {"coordinates": "{5.0, 3.0, 0}", "height": "1.01094"}, "83": {"coordinates": "{6.0, 3.0, 0}", "height": "0.967265"}, "84": {"coordinates": "{7.0, 3.0, 0}", "height": "0.832074"}, "85": {"coordinates": "{8.0, 3.0, 0}", "height": "0.615751"}, "86": {"coordinates": "{9.0, 3.0, 0}", "height": "0.329251"}, "87": {"coordinates": "{10.0, 3.0, 0}", "height": "0.462337"}, "88": {"coordinates": "{11.0, 3.0, 0}", "height": "0.54813"}, "89": {"coordinates": "{12.0, 3, 0}", "height": "0.551979"}, "90": {"coordinates": "{13, 3, 0}", "height": "0.450383"}, "91": {"coordinates": "{14, 3, 0}", "height": "0.26943"}, "92": {"coordinates": "{1.0, 4.0, 0}", "height": "0.412776"}, "93": {"coordinates": "{2.0, 4.0, 0}", "height": "0.808574"}, "94": {"coordinates": "{3.0, 4, 0}", "height": "1.044639"}, "95": {"coordinates": "{4.0, 4, 0}", "height": "1.1652"}, "96": {"coordinates": "{5.0, 4, 0}", "height": "1.283763"}, "97": {"coordinates": "{6.0, 4.0, 0}", "height": "1.304633"}, "98": {"coordinates": "{7.0, 4.0, 0}", "height": "1.191515"}, "99": {"coordinates": "{8.0, 4.0, 0}", "height": "0.895238"}, "100": {"coordinates": "{9.0, 4, 0}", "height": "0.367718"}, "101": {"coordinates": "{10.0, 4, 0}", "height": "0.545385"}, "102": {"coordinates": "{11.0, 4, 0}", "height": "0.699567"}, "103": {"coordinates": "{12.0, 4, 0}", "height": "0.702131"}, "104": {"coordinates": "{13, 4, 0}", "height": "0.655892"}, "105": {"coordinates": "{14, 4, 0}", "height": "0.411651"}, "106": {"coordinates": "{1.0, 5.0, 0}", "height": "0.440856"}, "107": {"coordinates": "{2.0, 5.0, 0}", "height": "0.83307"}, "108": {"coordinates": "{3.0, 5, 0}", "height": "1.100283"}, "109": {"coordinates": "{4.0, 5, 0}", "height": "1.252977"}, "110": {"coordinates": "{5.0, 5, 0}", "height": "1.345369"}, "111": {"coordinates": "{6.0, 5, 0}", "height": "1.310306"}, "112": {"coordinates": "{7.0, 5.0, 0}", "height": "1.133417"}, "113": {"coordinates": "{8.0, 5, 0}", "height": "0.820479"}, "114": {"coordinates": "{9.0, 5, 0}", "height": "0.38321"}, "115": {"coordinates": "{10.0, 5, 0}", "height": "0.576693"}, "116": {"coordinates": "{11.0, 5, 0}", "height": "0.723171"}, "117": {"coordinates": "{12, 5, 0}", "height": "0.74335"}, "118": {"coordinates": "{13, 5, 0}", "height": "0.632519"}, "119": {"coordinates": "{14, 5, 0}", "height": "0.388447"}, "120": {"coordinates": "{1.0, 6, 0}", "height": "0.444367"}, "121": {"coordinates": "{2, 6, 0}", "height": "0.88733"}, "122": {"coordinates": "{3, 6, 0}", "height": "1.152653"}, "123": {"coordinates": "{4, 6, 0}", "height": "1.285115"}, "124": {"coordinates": "{5, 6, 0}", "height": "1.440074"}, "125": {"coordinates": "{6, 6, 0}", "height": "1.464808"}, "126": {"coordinates": "{7, 6, 0}", "height": "1.306553"}, "127": {"coordinates": "{8.0, 6, 0}", "height": "0.938671"}, "128": {"coordinates": "{9.0, 6, 0}", "height": "0.358102"}, "129": {"coordinates": "{10.0, 6, 0}", "height": "0.574265"}, "130": {"coordinates": "{11, 6, 0}", "height": "0.773242"}, "131": {"coordinates": "{12, 6, 0}", "height": "0.801898"}, "132": {"coordinates": "{13, 6, 0}", "height": "0.741764"}, "133": {"coordinates": "{14, 6, 0}", "height": "0.474238"}, "134": {"coordinates": "{1.0, 7, 0}", "height": "0.40584"}, "135": {"coordinates": "{2.0, 7.0, 0}", "height": "0.890542"}, "136": {"coordinates": "{3, 7, 0}", "height": "1.111076"}, "137": {"coordinates": "{4.0, 7, 0}", "height": "1.188594"}, "138": {"coordinates": "{5, 7, 0}", "height": "1.413064"}, "139": {"coordinates": "{6, 7, 0}", "height": "1.547357"}, "140": {"coordinates": "{7, 7, 0}", "height": "1.508931"}, "141": {"coordinates": "{8, 7, 0}", "height": "1.155128"}, "142": {"coordinates": "{9, 7, 0}", "height": "0.302203"}, "143": {"coordinates": "{10.0, 7, 0}", "height": "0.519854"}, "144": {"coordinates": "{11, 7, 0}", "height": "0.773036"}, "145": {"coordinates": "{12, 7, 0}", "height": "0.784826"}, "146": {"coordinates": "{13, 7, 0}", "height": "0.860814"}, "147": {"coordinates": "{14, 7, 0}", "height": "0.563463"}, "148": {"coordinates": "{1.0, 8, 0}", "height": "0.319978"}, "149": {"coordinates": "{2.0, 8, 0}", "height": "0.663753"}, "150": {"coordinates": "{3, 8, 0}", "height": "0.860038"}, "151": {"coordinates": "{4, 8, 0}", "height": "0.950575"}, "152": {"coordinates": "{5, 8, 0}", "height": "1.097807"}, "153": {"coordinates": "{6, 8, 0}", "height": "1.13596"}, "154": {"coordinates": "{7, 8, 0}", "height": "1.008729"}, "155": {"coordinates": "{8, 8, 0}", "height": "0.701402"}, "156": {"coordinates": "{9, 8, 0}", "height": "0.229877"}, "157": {"coordinates": "{10.0, 8, 0}", "height": "0.40568"}, "158": {"coordinates": "{11, 8, 0}", "height": "0.58382"}, "159": {"coordinates": "{12, 8, 0}", "height": "0.621582"}, "160": {"coordinates": "{13, 8, 0}", "height": "0.588759"}, "161": {"coordinates": "{14, 8, 0}", "height": "0.385652"}, "162": {"coordinates": "{1, 9, 0}", "height": "0.18461"}, "163": {"coordinates": "{2, 9, 0}", "height": "0.456345"}, "164": {"coordinates": "{3, 9, 0}", "height": "0.543255"}, "165": {"coordinates": "{4, 9, 0}", "height": "0.549778"}, "166": {"coordinates": "{5, 9.0, 0}", "height": "0.708283"}, "167": {"coordinates": "{6, 9, 0}", "height": "0.843467"}, "168": {"coordinates": "{7, 9, 0}", "height": "0.886099"}, "169": {"coordinates": "{8, 9, 0}", "height": "0.700784"}, "170": {"coordinates": "{9, 9, 0}", "height": "0.12217"}, "171": {"coordinates": "{10.0, 9.0, 0}", "height": "0.233825"}, "172": {"coordinates": "{11, 9, 0}", "height": "0.39466"}, "173": {"coordinates": "{12, 9, 0}", "height": "0.39206"}, "174": {"coordinates": "{13.0, 9, 0}", "height": "0.506282"}, "175": {"coordinates": "{14, 9, 0}", "height": "0.341454"}}, "Size_y/m": 15.0}