{"Mass/kg": 39002.341820000001, "Size_x/m": 10.0, "Height_of_vault/m": 1.0232460000000001, "Thickness/m": 0.095000000000000001, "Height_of_each_node/m": {"0": {"coordinates": "{0, 0, 0}", "height": "0"}, "1": {"coordinates": "{1, 0, 0}", "height": "0"}, "2": {"coordinates": "{2, 0, 0}", "height": "0"}, "3": {"coordinates": "{3, 0, 0}", "height": "0"}, "4": {"coordinates": "{4, 0, 0}", "height": "0"}, "5": {"coordinates": "{5, 0, 0}", "height": "0"}, "6": {"coordinates": "{6, 0, 0}", "height": "0"}, "7": {"coordinates": "{7, 0, 0}", "height": "0"}, "8": {"coordinates": "{8, 0, 0}", "height": "0"}, "9": {"coordinates": "{9, 0, 0}", "height": "0"}, "10": {"coordinates": "{10, 0, 0}", "height": "0"}, "11": {"coordinates": "{11, 0, 0}", "height": "0"}, "12": {"coordinates": "{12, 0, 0}", "height": "0"}, "13": {"coordinates": "{13, 0, 0}", "height": "0"}, "14": {"coordinates": "{14, 0, 0}", "height": "0"}, "15": {"coordinates": "{15, 0, 0}", "height": "0"}, "16": {"coordinates": "{0, 1, 0}", "height": "0"}, "17": {"coordinates": "{15, 1, 0}", "height": "0"}, "18": {"coordinates": "{0, 2, 0}", "height": "0"}, "19": {"coordinates": "{15, 2, 0}", "height": "0"}, "20": {"coordinates": "{0, 3, 0}", "height": "0"}, "21": {"coordinates": "{15, 3, 0}", "height": "0"}, "22": {"coordinates": "{0, 4, 0}", "height": "0"}, "23": {"coordinates": "{15, 4, 0}", "height": "0"}, "24": {"coordinates": "{0, 5, 0}", "height": "0"}, "25": {"coordinates": "{15, 5, 0}", "height": "0"}, "26": {"coordinates": "{0, 6, 0}", "height": "0"}, "27": {"coordinates": "{15, 6, 0}", "height": "0"}, "28": {"coordinates": "{0, 7, 0}", "height": "0"}, "29": {"coordinates": "{15, 7, 0}", "height": "0"}, "30": {"coordinates": "{0, 8, 0}", "height": "0"}, "31": {"coordinates": "{15, 8, 0}", "height": "0"}, "32": {"coordinates": "{0, 9, 0}", "height": "0"}, "33": {"coordinates": "{15, 9, 0}", "height": "0"}, "34": {"coordinates": "{0, 10, 0}", "height": "0"}, "35": {"coordinates": "{1, 10, 0}", "height": "0"}, "36": {"coordinates": "{2, 10, 0}", "height": "0"}, "37": {"coordinates": "{3, 10, 0}", "height": "0"}, "38": {"coordinates": "{4, 10, 0}", "height": "0"}, "39": {"coordinates": "{5, 10, 0}", "height": "0"}, "40": {"coordinates": "{6, 10, 0}", "height": "0"}, "41": {"coordinates": "{7, 10, 0}", "height": "0"}, "42": {"coordinates": "{8, 10, 0}", "height": "0"}, "43": {"coordinates": "{9, 10, 0}", "height": "0"}, "44": {"coordinates": "{10, 10, 0}", "height": "0"}, "45": {"coordinates": "{11, 10, 0}", "height": "0"}, "46": {"coordinates": "{12, 10, 0}", "height": "0"}, "47": {"coordinates": "{13, 10, 0}", "height": "0"}, "48": {"coordinates": "{14, 10, 0}", "height": "0"}, "49": {"coordinates": "{15, 10, 0}", "height": "0"}, "50": {"coordinates": "{1.0, 1.0, 0}", "height": "0.060115"}, "51": {"coordinates": "{2.0, 1.0, 0}", "height": "0.107194"}, "52": {"coordinates": "{3.0, 1.0, 0}", "height": "0.14196"}, "53": {"coordinates": "{4.0, 1.0, 0}", "height": "0.167846"}, "54": {"coordinates": "{5.0, 1.0, 0}", "height": "0.185288"}, "55": {"coordinates": "{6.0, 1.0, 0}", "height": "0.200074"}, "56": {"coordinates": "{7.0, 1.0, 0}", "height": "0.204624"}, "57": {"coordinates": "{8, 1.0, 0}", "height": "0.199075"}, "58": {"coordinates": "{9.0, 1.0, 0}", "height": "0.181018"}, "59": {"coordinates": "{10.0, 1.0, 0}", "height": "0.175978"}, "60": {"coordinates": "{11.0, 1.0, 0}", "height": "0.158315"}, "61": {"coordinates": "{12.0, 1.0, 0}", "height": "0.135096"}, "62": {"coordinates": "{13.0, 1.0, 0}", "height": "0.101757"}, "63": {"coordinates": "{14.0, 1.0, 0}", "height": "0.056775"}, "64": {"coordinates": "{1.0, 2, 0}", "height": "0.083972"}, "65": {"coordinates": "{2.0, 2, 0}", "height": "0.160253"}, "66": {"coordinates": "{3.0, 2, 0}", "height": "0.227707"}, "67": {"coordinates": "{4.0, 2.0, 0}", "height": "0.280903"}, "68": {"coordinates": "{5.0, 2.0, 0}", "height": "0.319666"}, "69": {"coordinates": "{6.0, 2.0, 0}", "height": "0.337167"}, "70": {"coordinates": "{7.0, 2.0, 0}", "height": "0.343554"}, "71": {"coordinates": "{8.0, 2.0, 0}", "height": "0.339011"}, "72": {"coordinates": "{9, 2.0, 0}", "height": "0.326514"}, "73": {"coordinates": "{10, 2.0, 0}", "height": "0.300319"}, "74": {"coordinates": "{11, 2.0, 0}", "height": "0.266287"}, "75": {"coordinates": "{12, 2, 0}", "height": "0.215774"}, "76": {"coordinates": "{13, 2, 0}", "height": "0.153551"}, "77": {"coordinates": "{14, 2, 0}", "height": "0.081582"}, "78": {"coordinates": "{1.0, 3, 0}", "height": "0.209019"}, "79": {"coordinates": "{2.0, 3.0, 0}", "height": "0.369674"}, "80": {"coordinates": "{3.0, 3, 0}", "height": "0.479185"}, "81": {"coordinates": "{4.0, 3.0, 0}", "height": "0.544903"}, "82": {"coordinates": "{5.0, 3.0, 0}", "height": "0.579381"}, "83": {"coordinates": "{6.0, 3.0, 0}", "height": "0.62212"}, "84": {"coordinates": "{7.0, 3.0, 0}", "height": "0.6235"}, "85": {"coordinates": "{8.0, 3.0, 0}", "height": "0.57907"}, "86": {"coordinates": "{9, 3.0, 0}", "height": "0.488516"}, "87": {"coordinates": "{10, 3.0, 0}", "height": "0.510151"}, "88": {"coordinates": "{11, 3, 0}", "height": "0.486535"}, "89": {"coordinates": "{12, 3, 0}", "height": "0.43821"}, "90": {"coordinates": "{13, 3, 0}", "height": "0.343711"}, "91": {"coordinates": "{14, 3, 0}", "height": "0.198321"}, "92": {"coordinates": "{1.0, 4.0, 0}", "height": "0.451656"}, "93": {"coordinates": "{2.0, 4, 0}", "height": "0.679589"}, "94": {"coordinates": "{3.0, 4, 0}", "height": "0.728219"}, "95": {"coordinates": "{4.0, 4, 0}", "height": "0.76489"}, "96": {"coordinates": "{5.0, 4.0, 0}", "height": "0.763801"}, "97": {"coordinates": "{6.0, 4.0, 0}", "height": "0.888569"}, "98": {"coordinates": "{7.0, 4.0, 0}", "height": "0.911631"}, "99": {"coordinates": "{8.0, 4.0, 0}", "height": "0.852739"}, "100": {"coordinates": "{9.0, 4.0, 0}", "height": "0.587018"}, "101": {"coordinates": "{10, 4.0, 0}", "height": "0.736132"}, "102": {"coordinates": "{11, 4, 0}", "height": "0.668584"}, "103": {"coordinates": "{12, 4.0, 0}", "height": "0.66929"}, "104": {"coordinates": "{13.0, 4.0, 0}", "height": "0.589136"}, "105": {"coordinates": "{14, 4.0, 0}", "height": "0.365979"}, "106": {"coordinates": "{1.0, 5, 0}", "height": "0.591432"}, "107": {"coordinates": "{2.0, 5, 0}", "height": "0.815921"}, "108": {"coordinates": "{3.0, 5, 0}", "height": "0.818808"}, "109": {"coordinates": "{4.0, 5, 0}", "height": "0.859803"}, "110": {"coordinates": "{5.0, 5.0, 0}", "height": "0.851766"}, "111": {"coordinates": "{6.0, 5.0, 0}", "height": "1.000228"}, "112": {"coordinates": "{7.0, 5.0, 0}", "height": "1.023246"}, "113": {"coordinates": "{8.0, 5.0, 0}", "height": "0.995895"}, "114": {"coordinates": "{9.0, 5.0, 0}", "height": "0.636669"}, "115": {"coordinates": "{10.0, 5.0, 0}", "height": "0.867646"}, "116": {"coordinates": "{11, 5, 0}", "height": "0.740393"}, "117": {"coordinates": "{12, 5.0, 0}", "height": "0.752267"}, "118": {"coordinates": "{13, 5.0, 0}", "height": "0.67833"}, "119": {"coordinates": "{14, 5.0, 0}", "height": "0.424074"}, "120": {"coordinates": "{1.0, 6.0, 0}", "height": "0.315234"}, "121": {"coordinates": "{2.0, 6, 0}", "height": "0.562587"}, "122": {"coordinates": "{3.0, 6, 0}", "height": "0.730823"}, "123": {"coordinates": "{4.0, 6, 0}", "height": "0.820189"}, "124": {"coordinates": "{5.0, 6, 0}", "height": "0.857608"}, "125": {"coordinates": "{6.0, 6.0, 0}", "height": "0.907943"}, "126": {"coordinates": "{7.0, 6.0, 0}", "height": "0.893377"}, "127": {"coordinates": "{8.0, 6.0, 0}", "height": "0.803285"}, "128": {"coordinates": "{9.0, 6.0, 0}", "height": "0.648363"}, "129": {"coordinates": "{10.0, 6.0, 0}", "height": "0.707322"}, "130": {"coordinates": "{11, 6, 0}", "height": "0.703741"}, "131": {"coordinates": "{12, 6, 0}", "height": "0.648778"}, "132": {"coordinates": "{13, 6, 0}", "height": "0.51537"}, "133": {"coordinates": "{14, 6, 0}", "height": "0.300411"}, "134": {"coordinates": "{1, 7, 0}", "height": "0.402749"}, "135": {"coordinates": "{2.0, 7, 0}", "height": "0.631548"}, "136": {"coordinates": "{3.0, 7, 0}", "height": "0.722639"}, "137": {"coordinates": "{4.0, 7, 0}", "height": "0.776723"}, "138": {"coordinates": "{5.0, 7, 0}", "height": "0.78458"}, "139": {"coordinates": "{6.0, 7, 0}", "height": "0.8735"}, "140": {"coordinates": "{7.0, 7.0, 0}", "height": "0.874476"}, "141": {"coordinates": "{8.0, 7.0, 0}", "height": "0.802268"}, "142": {"coordinates": "{9.0, 7.0, 0}", "height": "0.569783"}, "143": {"coordinates": "{10.0, 7.0, 0}", "height": "0.700426"}, "144": {"coordinates": "{11, 7.0, 0}", "height": "0.663943"}, "145": {"coordinates": "{12, 7, 0}", "height": "0.64992"}, "146": {"coordinates": "{13, 7.0, 0}", "height": "0.553965"}, "147": {"coordinates": "{14, 7, 0}", "height": "0.337343"}, "148": {"coordinates": "{1.0, 8, 0}", "height": "0.287606"}, "149": {"coordinates": "{2, 8, 0}", "height": "0.481392"}, "150": {"coordinates": "{3, 8, 0}", "height": "0.577856"}, "151": {"coordinates": "{4.0, 8, 0}", "height": "0.618497"}, "152": {"coordinates": "{5.0, 8, 0}", "height": "0.62297"}, "153": {"coordinates": "{6.0, 8.0, 0}", "height": "0.686715"}, "154": {"coordinates": "{7.0, 8, 0}", "height": "0.684047"}, "155": {"coordinates": "{8.0, 8.0, 0}", "height": "0.606903"}, "156": {"coordinates": "{9.0, 8.0, 0}", "height": "0.441287"}, "157": {"coordinates": "{10.0, 8.0, 0}", "height": "0.528861"}, "158": {"coordinates": "{11.0, 8.0, 0}", "height": "0.528704"}, "159": {"coordinates": "{12, 8.0, 0}", "height": "0.517598"}, "160": {"coordinates": "{13, 8.0, 0}", "height": "0.435704"}, "161": {"coordinates": "{14.0, 8.0, 0}", "height": "0.264544"}, "162": {"coordinates": "{1, 9, 0}", "height": "0.434088"}, "163": {"coordinates": "{2, 9, 0}", "height": "0.491795"}, "164": {"coordinates": "{3, 9, 0}", "height": "0.385032"}, "165": {"coordinates": "{4.0, 9, 0}", "height": "0.380438"}, "166": {"coordinates": "{5.0, 9.0, 0}", "height": "0.349885"}, "167": {"coordinates": "{6, 9, 0}", "height": "0.459073"}, "168": {"coordinates": "{7.0, 9, 0}", "height": "0.480168"}, "169": {"coordinates": "{8, 9, 0}", "height": "0.52532"}, "170": {"coordinates": "{9, 9.0, 0}", "height": "0.236609"}, "171": {"coordinates": "{10.0, 9.0, 0}", "height": "0.462678"}, "172": {"coordinates": "{11.0, 9.0, 0}", "height": "0.319453"}, "173": {"coordinates": "{12.0, 9.0, 0}", "height": "0.363622"}, "174": {"coordinates": "{13.0, 9.0, 0}", "height": "0.370065"}, "175": {"coordinates": "{14, 9.0, 0}", "height": "0.242584"}}, "Size_y/m": 15.0}